MANIFEST.in
README.txt
setup.py
src/requires.txt
src/m3_report_generator.egg-info/PKG-INFO
src/m3_report_generator.egg-info/SOURCES.txt
src/m3_report_generator.egg-info/dependency_links.txt
src/m3_report_generator.egg-info/top_level.txt
src/report_generator/__init__.py
src/report_generator/app_meta.py
src/report_generator/constructor_settings.py
src/report_generator/exceptions.py
src/report_generator/renderer.py
src/report_generator/ui.py
src/report_generator/version.py
src/report_generator/api/__init__.py
src/report_generator/api/api.py
src/report_generator/core/__init__.py
src/report_generator/core/alchemy_wrapper.py
src/report_generator/core/builder.py
src/report_generator/core/db_wrapper.py
src/report_generator/core/entity_proxy.py
src/report_generator/core/helpers.py
src/report_generator/core/proxy.py
src/report_generator/core/query_components.py
src/report_generator/query_builder/__init__.py
src/report_generator/query_builder/actions.py
src/report_generator/query_builder/app_meta.py
src/report_generator/query_builder/entity_proxy.py
src/report_generator/query_builder/models.py
src/report_generator/query_builder/proxy.py
src/report_generator/query_builder/ui.py
src/report_generator/query_builder/migrations/0001_initial.py
src/report_generator/query_builder/migrations/__init__.py
src/report_generator/query_builder/templates/qb-add-condition-window.js
src/report_generator/query_builder/templates/qb-connection-window.js
src/report_generator/query_builder/templates/qb-window.js
src/report_generator/report_builder/__init__.py
src/report_generator/report_builder/actions.py
src/report_generator/report_builder/api.py
src/report_generator/report_builder/app_meta.py
src/report_generator/report_builder/builder.py
src/report_generator/report_builder/enums.py
src/report_generator/report_builder/models.py
src/report_generator/report_builder/proxy.py
src/report_generator/report_builder/ui.py
src/report_generator/report_builder/migrations/0001_initial.py
src/report_generator/report_builder/migrations/0002_add_field_Template_report.py
src/report_generator/report_builder/migrations/0003_add_model_FormField.py
